satmarg/__init__.py
satmarg/core.py
satmarg-0.3.2.dist-info/licenses/LICENSE.txt
satmarg-0.3.2.dist-info/METADATA
satmarg-0.3.2.dist-info/WHEEL
satmarg-0.3.2.dist-info/top_level.txt
satmarg-0.3.2.dist-info/RECORD
