Metadata-Version: 2.4
Name: satmarg
Version: 0.3.2
Summary: Predict satellite overpasses based on TLE and user location
Author-email: Upendra Oli <upendra.oli59@gmail.com>
License-Expression: GPL-3.0-or-later
License-File: LICENSE.txt
Requires-Dist: skyfield
Requires-Dist: numpy
Requires-Dist: pandas
Requires-Dist: requests
Dynamic: license-file
